MANIFEST.in
README.md
setup.py
django_rango.egg-info/PKG-INFO
django_rango.egg-info/SOURCES.txt
django_rango.egg-info/dependency_links.txt
django_rango.egg-info/top_level.txt
rango/__init__.py
rango/cache.py
rango/middleware.py
rango/router.py
rango/utils.py