Metadata-Version: 1.0
Name: django-rango
Version: 0.0.5
Summary: A database router based on incoming host address.
Home-page: https://github.com/mmmdamin/django-rango
Author: Amin Sabbaghian
Author-email: mmmdamin@gmail.com
License: MIT
Platform: UNKNOWN
